{
  "name": "Emily Massey",
  "age": 55,
  "address": {
    "street": "Bitkov Pass",
    "city": "Pokrompu",
    "state": "WI",
    "zip": "16735"
  },
  "contact": {
    "phone": "(404) 529-2710",
    "servicePhone": "800317411"
  },
  "birthday": "1967-09-16T23:58:57.010Z",
  "ip": "154.95.66.32",
  "foo": "bar",
  "profile": {
    "about": "Ha walbudoz do ezegan nobig na ehilevud neize akaoki gobopipo loame wad ji. Ba bo ugiic hu mon otuumfo jo eni an ekmofe sed pagvusog ivukal tab go vihemij. Obeegiegu velredo zuredcis miez nipanho koku puka lecniafa tervogu no ame voznod dod. Eki fu poheppi gifkep kovcowo asiuw muho ik mihifid nena mak as wab no.",
    "bio": "Tafuv ir ziggoneb damovzof kedus bus ivohi uwkosi lalsu ij kabrujiv wafih on teknowze du wuvame. Wu za isworo use ha ownivu ub tecsu su ven buuncu duekfe wo lakofop. Pena davga weja jamug afjawi ku lalsa senbik huvdon ehrezmuw malo sub ociegu jereg mal. Zog pik sor ujowow diton to daloz sogoj amounu nisnilub famom amiem hej."
  },
  "apiKey": "77b715bbb76d6d88ebfe8d3a9dba3e3ac914dfb85214b34cd4a2e858562f888b",
  "currency": {
    "code": "SPL",
    "name": "Seborga Luigino"
  }
}