{
  "name": "Betty Lewis",
  "age": 31,
  "address": {
    "street": "Daedu Turnpike",
    "city": "Wasvompa",
    "state": "MN",
    "zip": "56510"
  },
  "contact": {
    "phone": "(578) 735-8715",
    "servicePhone": "800276836"
  },
  "birthday": "1983-09-25T19:49:03.757Z",
  "ip": "169.241.64.64",
  "foo": "bar",
  "profile": {
    "about": "Di susvejo kesis vo caago judhig bihholaf fiojha kicnap peroj husrojo dosahuce popuco. Kuzbetuk kopnic zuful jepnek daj mawdupa ov nusitkiv so zotrur tosma pikib olna. Tah hehoela bezejo lihib ciutu kewrov ipaik opukuji fukub ecin moovpab medbasnaj vaveeru. Bughum wetersob to evdejunu letcogo vednaliv vesulci ilbisu pawfo gihifi hu og jo awanes zote pazi nopan. Awfoflak cihgomo foz mowbu calok zi va ifupo dejad cajlaw afomac owomaw ev.",
    "bio": "Goda ju ok muwur fadzom biccomaw ubi dirak tujassa vaad leg pinete pemovu hawokot seuk feddik. Cig ap jo gouce su wok buziwid ruzed koc gefrela jit firohon tor ek apomu ginufi besde osdi. Kajzag kozkov efset an eziloapa serure new se asuibojef eca newcufepi degaih coil zidusmep rashiwu. Roogku majival mav gazuco tabuz zigbago wo ne rebug neslufzo ewnedema ojoho ig raca izupibha rohiz leirij. Ur libbawo ce hioguwaz jeh huzwe ibawutaw pabsor ase nuhmaprom vehpawuj aluow. Di lo muzvo wan kevehu cad je vulob waunu nutiz lo jivov ovopu hetco kaep. Fa zoripic kohwogzu le panid uvonez zevaura zimijim ivzerpa dolune aj nesup sitheceki fur."
  },
  "apiKey": "75e9aaf115b82ae5b166e352693ddf9cb24f28fe7363f8e626e2e75b78fe44cb",
  "currency": {
    "code": "UZS",
    "name": "Uzbekistan Som"
  }
}